liteevallogger/__init__.py
liteevallogger-0.1.0.dist-info/METADATA
liteevallogger-0.1.0.dist-info/WHEEL
liteevallogger-0.1.0.dist-info/top_level.txt
liteevallogger-0.1.0.dist-info/RECORD
