Metadata-Version: 2.4
Name: liteevallogger
Version: 0.1.0
Summary: Lightweight evaluation logger built on top of Weave
Author-email: Your Name <you@example.com>
Requires-Python: >=3.9
Requires-Dist: weave
